mcp_jira/__init__.py
mcp_jira/server.py
jira_mcp_tools-0.2.1.dist-info/METADATA
jira_mcp_tools-0.2.1.dist-info/WHEEL
jira_mcp_tools-0.2.1.dist-info/entry_points.txt
jira_mcp_tools-0.2.1.dist-info/licenses/LICENSE
jira_mcp_tools-0.2.1.dist-info/RECORD
