Metadata-Version: 2.4
Name: jira-mcp-tools
Version: 0.2.1
Summary: Model Context Protocol server for Jira integration
Project-URL: Homepage, https://github.com/IBM/jira-mcp-tools
Project-URL: Repository, https://github.com/IBM/jira-mcp-tools
Project-URL: Issues, https://github.com/IBM/jira-mcp-tools/issues
Author-email: IBM <opensource@ibm.com>
License: MIT
License-File: LICENSE
Keywords: ai,jira,llm,mcp,model-context-protocol
Classifier: Development Status :: 4 - Beta
Classifier: Intended Audience :: Developers
Classifier: License :: OSI Approved :: MIT License
Classifier: Programming Language :: Python :: 3
Classifier: Programming Language :: Python :: 3.10
Classifier: Programming Language :: Python :: 3.11
Classifier: Programming Language :: Python :: 3.12
Classifier: Topic :: Software Development :: Libraries :: Python Modules
Requires-Python: >=3.10
Requires-Dist: click>=8.0.0
Requires-Dist: fastmcp>=2.6.1
Requires-Dist: jira>=3.4.0
Requires-Dist: python-dotenv>=1.0.0
Requires-Dist: requests>=2.32.5
Requires-Dist: ruff>=0.11.0
